psivideo/__init__.py
psivideo/capture.py
psivideo/client.py
psivideo/display.py
psivideo/main.py
psivideo/process.py
psivideo/tcp.py
psivideo/version.py
psivideo/video.py
psivideo/write.py
psivideo-0.0.1.dist-info/LICENSE.txt
psivideo-0.0.1.dist-info/METADATA
psivideo-0.0.1.dist-info/WHEEL
psivideo-0.0.1.dist-info/entry_points.txt
psivideo-0.0.1.dist-info/top_level.txt
psivideo-0.0.1.dist-info/RECORD
